pyqterm
