Metadata-Version: 1.0
Name: pyqterm
Version: 0.1
Summary: Simple terminal/console widget for PyQt4 with vt100 support
Home-page: UNKNOWN
Author: Henning Schroeder
Author-email: henning.schroeder@gmail.com
License: GPL2
Keywords: pyqt pyqt4 console terminal shell vt100 widget
Platform: UNKNOWN
